thermaPy/__init__.py
thermaPy/main.py
thermaPy-0.0.2.dist-info/LICENSE
thermaPy-0.0.2.dist-info/METADATA
thermaPy-0.0.2.dist-info/WHEEL
thermaPy-0.0.2.dist-info/top_level.txt
thermaPy-0.0.2.dist-info/RECORD
