Metadata-Version: 2.1
Name: thermaPy
Version: 0.0.2
License-File: LICENSE
Requires-Dist: opencv-python (>=4.9.0.80)
Requires-Dist: matplotlib (>=3.7.2)
Requires-Dist: scikit-image
Requires-Dist: pandas
Requires-Dist: numpy
